{
  "date": "2026-04-30",
  "date_human": "30 April 2026",
  "generated_at": "2026-04-30T04:04:47.540159+00:00",
  "stats": {
    "feeds_collected": 276,
    "news_total": 5331,
    "news_analyzed": 611,
    "clusters": 11
  },
  "mood": {
    "description": "Küresel gerilimlerin ve ekonomik dalgalanmaların gölgesinde, teknoloji ve sanat dünyasındaki yeniliklerin umut aşıladığı, ancak gündelik yaşamın da önemli olaylarla dolu olduğu bir gün.",
    "dominant_emotion": "Belirsizlik",
    "key_themes": [
      "Küresel jeopolitik gerilimler ve diplomatik temaslar",
      "Teknoloji ve yapay zeka alanındaki gelişmeler ve yatırımlar",
      "Ekonomik dalgalanmalar ve faiz kararları",
      "Spor dünyasında şampiyonluklar ve transfer hareketliliği",
      "Sanat ve eğlence sektöründeki yeni projeler ve etkinlikler"
    ]
  },
  "weather": {
    "location": "İzmir",
    "latitude": 38.4192,
    "longitude": 27.1287,
    "days": [
      {
        "date": "2026-04-30",
        "code": 2,
        "temp_max": 26.8,
        "temp_min": 10.4
      },
      {
        "date": "2026-05-01",
        "code": 80,
        "temp_max": 17.0,
        "temp_min": 11.4
      },
      {
        "date": "2026-05-02",
        "code": 3,
        "temp_max": 18.1,
        "temp_min": 9.4
      },
      {
        "date": "2026-05-03",
        "code": 61,
        "temp_max": 15.4,
        "temp_min": 8.6
      },
      {
        "date": "2026-05-04",
        "code": 3,
        "temp_max": 18.6,
        "temp_min": 6.3
      },
      {
        "date": "2026-05-05",
        "code": 1,
        "temp_max": 22.8,
        "temp_min": 9.0
      },
      {
        "date": "2026-05-06",
        "code": 2,
        "temp_max": 26.3,
        "temp_min": 12.5
      }
    ]
  },
  "clusters": [
    {
      "title": "Küresel Gerilimler ve Diplomatik Hamleler",
      "meta_category": "Politika ve Diplomasi",
      "summary": "İran'a yönelik abluka ve ABD-İran gerilimi ön plana çıkarken, Dışişleri Bakanı Fidan'ın Avusturya ve İspanya mevkidaşlarıyla görüşmeleri ve Küresel Sumud Filosu'na İsrail müdahalesi uluslararası ilişkilerdeki hassasiyeti gösteriyor. Savaşların ekonomik etkileri ve diplomatik açıklamalar da bu kümede yer alıyor.",
      "importance": 9,
      "story_count": 52,
      "stories": [
        {
          "title": "Dışişleri Bakanı Fidan, İspanyol mevkidaşıyla Küresel Sumud Filosu'na yasa dışı müdahaleyi görüştü",
          "source": "Anadolu Ajansı",
          "link": "https://www.aa.com.tr/tr/gundem/disisleri-bakani-fidan-ispanyol-mevkidasiyla-kuresel-sumud-filosuna-yasa-disi-mudahaleyi-gorustu/3922343",
          "also_in": [
            "dikGAZETE",
            "Haber Global",
            "TRT Haber"
          ]
        },
        {
          "title": "İran medyası: ABD'nin deniz ablukasına yakında \"emsalsiz bir eylemle\" karşılık verilecek",
          "source": "Evrensel",
          "link": "https://www.evrensel.net/haber/5981924/iran-medyasi-abdnin-deniz-ablukasina-yakinda-emsalsiz-bir-eylemle-karsilik-verilecek?utm_source=rss_feed&utm_medium=rss&utm_campaign=rss_syndication",
          "also_in": [
            "İstiklal",
            "Sputnik",
            "TRT Haber"
          ]
        },
        {
          "title": "Dışişleri Bakanı Fidan, Avusturya Başbakanı Stocker tarafından kabul edildi",
          "source": "Diriliş Postası",
          "link": "https://www.dirilispostasi.com/disisleri-bakani-fidan-avusturya-basbakani-stocker-tarafindan-kabul-edildi",
          "also_in": [
            "dikGAZETE",
            "Haberler"
          ]
        },
        {
          "title": "İsrail basını: Trump ve Netanyahu, Lübnan ve İran meselelerini görüştü",
          "source": "Evrensel",
          "link": "https://www.evrensel.net/haber/5981936/israil-basini-trump-ve-netanyahu-lubnan-ve-iran-meselelerini-gorustu?utm_source=rss_feed&utm_medium=rss&utm_campaign=rss_syndication",
          "also_in": [
            "Haberler",
            "Yeniçağ Gazetesi"
          ]
        },
        {
          "title": "İsrail'den Sumud filosuna müdahale",
          "source": "Ekonomim",
          "link": "https://www.ekonomim.com/dunya/israilden-sumud-filosuna-mudahale-haberi-891220",
          "also_in": [
            "İstiklal",
            "OdaTV"
          ]
        }
      ]
    },
    {
      "title": "Ekonomik Kararlar ve Piyasa Hareketleri",
      "meta_category": "Ekonomi ve Piyasalar",
      "summary": "ABD Merkez Bankası'nın (Fed) faiz kararını açıklaması, piyasalarda önemli bir gündem maddesi oldu. Euro Bölgesi'nde ekonomik güvenin düşmesi, petrol fiyatlarındaki sert yükseliş ve gıda enflasyonundaki artış gibi gelişmeler ekonomik belirsizliği artırdı. Türkiye'de ise işsizlik rakamları ve sektör daralmaları öne çıktı.",
      "importance": 8,
      "story_count": 72,
      "stories": [
        {
          "title": "İkinci el piyasasında ezber bozan karar: Yetki belgesinde eğitim kriteri esnetildi",
          "source": "Megabayt",
          "link": "https://www.megabayt.com/otomobil/ikinci-el-piyasasinda-ezber-bozan-karar-yetki-belgesinde-egitim-kriteri-esnetildi/102235",
          "also_in": [
            "Megabayt Otomobil"
          ]
        },
        {
          "title": "FIFA’dan Dünya Kupası’na katılacak ülkelere 871 milyon dolar",
          "source": "Campaign Türkiye",
          "link": "https://www.campaigntr.com/haberler/fifadan-dunya-kupasina-katilacak-ulkelere-871-milyon-dolar/",
          "also_in": []
        },
        {
          "title": "Fed faiz kararını açıkladı",
          "source": "F5 Haber",
          "link": "https://www.f5haber.com/ekonomi/fed-faiz-kararini-acikladi-6913595",
          "also_in": [
            "Evrensel",
            "Ekonomim",
            "Gazete Pencere",
            "İnternet Haber",
            "İstiklal",
            "Haberler",
            "OdaTV",
            "CNBC-e",
            "Yurtsever"
          ]
        },
        {
          "title": "Kırsal Kalkınma Yatırım Programı 2026 başvuru dönemi başladı",
          "source": "Diriliş Postası",
          "link": "https://www.dirilispostasi.com/kirsal-kalkinma-yatirim-programi-2026-basvuru-donemi-basladi",
          "also_in": [
            "dikGAZETE",
            "Haberler",
            "Bigpara"
          ]
        },
        {
          "title": "New York borsası karışık seyirle kapandı",
          "source": "Dünya",
          "link": "https://www.dunya.com/finans/haberler/new-york-borsasi-karisik-seyirle-kapandi-haberi-823381",
          "also_in": [
            "Haberler",
            "Türkgün",
            "Yeniçağ Gazetesi"
          ]
        }
      ]
    },
    {
      "title": "Teknoloji Sektöründe Yenilikler ve Gelişmeler",
      "meta_category": "Bilim ve Teknoloji",
      "summary": "Teknoloji dünyası, Japon otomotiv devlerinin Türkiye'ye dönüşü, yeni elektrikli araç modelleri, akıllı telefonlar, kablosuz mikrofonlar ve yapay zeka alanındaki gelişmelerle hareketli bir gün geçirdi. Kanser tedavisindeki buluşlar ve dijital güvenlik çözümleri de dikkat çekti.",
      "importance": 8,
      "story_count": 50,
      "stories": [
        {
          "title": "Japon otomotiv devi Türkiye'ye geri dönüyor",
          "source": "Teknolojioku",
          "link": "https://www.teknolojioku.com/guncel/japon-otomotiv-devi-turkiyeye-geri-donuyor-69f21f4eeb986c177506d6da",
          "also_in": [
            "F5 Haber",
            "Sözcü Ekonomi"
          ]
        },
        {
          "title": "Minik Çinli elektrikli 7 bin dolara 310 km menzil vadediyor",
          "source": "Donanım Haber",
          "link": "https://www.donanimhaber.com/minik-cinli-elektrikli-7-bin-dolara-310-km-menzil-vadediyor--205040",
          "also_in": [
            "Teknolojioku"
          ]
        },
        {
          "title": "Xiaomi'nin yeni yongası ortaya çıktı",
          "source": "Donanım Haber",
          "link": "https://www.donanimhaber.com/xring-o3-geliyor--205057",
          "also_in": [
            "Teknolojioku"
          ]
        },
        {
          "title": "Google Translate 20 yaşında: En çok istenen özellik sonunda geldi",
          "source": "Donanım Haber",
          "link": "https://www.donanimhaber.com/google-translate-20-yasinda-en-cok-istenen-ozellik-sonunda-geldi--205053",
          "also_in": [
            "Teknodiot"
          ]
        },
        {
          "title": "DJI'dan kompakt kablosuz mikrofon: DJI Mic Mini 2",
          "source": "Donanım Haber",
          "link": "https://www.donanimhaber.com/dji-mic-mini-2-tanitildi-iste-fiyati-ve-ozellikleri--205045",
          "also_in": [
            "Teknolojioku"
          ]
        }
      ]
    },
    {
      "title": "Spor Dünyasında Şampiyonluklar ve Transfer Haberleri",
      "meta_category": "Spor",
      "summary": "Erzurumspor FK'nın şampiyonluk kutlamaları ve kupasını alması spor gündeminin en önemli başlıklarındandı. Transfer döneminin hareketlenmesiyle Beşiktaş, Trabzonspor ve Galatasaray'ın adı birçok oyuncuyla anılırken, Fenerbahçe'de de başkanlık adaylığı ve transfer gelişmeleri takip edildi. Atletico Madrid-Arsenal maçı ise nefesleri kesti.",
      "importance": 7,
      "story_count": 82,
      "stories": [
        {
          "title": "Erzurumspor şampiyonluk turu attı",
          "source": "NTV Spor Anasayfa",
          "link": "https://www.ntvspor.net/foto-galeri/erzurumspor-sampiyonluk-turu-atti-421950",
          "also_in": [
            "NTV Spor Futbol",
            "Fotospor",
            "dikGAZETE",
            "Haberler"
          ]
        },
        {
          "title": "Erzurumspor FK şampiyonluk kupasını aldı!",
          "source": "A Spor",
          "link": "https://www.aspor.com.tr/tff-birinci-lig/2026/04/29/erzurumspor-fk-sampiyonluk-kupasini-aldi",
          "also_in": [
            "Fotomaç",
            "Halk TV",
            "Medya Gazete"
          ]
        },
        {
          "title": "İspanya'da rakibine yumruk atan Arjantinli kaleci Andrada'ya 13 maçlık rekor ceza!",
          "source": "Fotomaç",
          "link": "https://www.fotomac.com.tr/futbol/2026/04/29/ispanyada-rakibine-yumruk-atan-arjantinli-kaleci-andradaya-13-maclik-rekor-ceza",
          "also_in": [
            "Diriliş Postası",
            "dikGAZETE",
            "TRT Haber"
          ]
        },
        {
          "title": "Beşiktaş'tan transfer operasyonu! 4 isim...",
          "source": "A Spor",
          "link": "https://www.aspor.com.tr/besiktas/2026/04/29/besiktastan-transfer-operasyonu-4-isim",
          "also_in": [
            "Fotomaç",
            "Duhuliye"
          ]
        },
        {
          "title": "Trabzonspor Başkanı Ertuğrul Doğan: İstanbul merkezli düzene karşı...",
          "source": "A Spor",
          "link": "https://www.aspor.com.tr/trabzonspor/2026/04/29/trabzonspor-baskani-ertugrul-dogan-istanbul-merkezli-duzene-karsi",
          "also_in": [
            "Fotomaç"
          ]
        }
      ]
    },
    {
      "title": "Toplumsal ve Günlük Yaşamdan Haberler",
      "meta_category": "Toplum ve Yaşam",
      "summary": "Gündelik yaşamı etkileyen çeşitli olaylar, kazalar, hukuki gelişmeler ve toplumsal konular haberlerde yer buldu. Hakim ve savcı atamaları, trafik kazaları, şiddet olayları ve eğitimle ilgili düzenlemeler günün dikkat çeken başlıkları arasındaydı.",
      "importance": 6,
      "story_count": 185,
      "stories": [
        {
          "title": "Bir WhatsApp mesajıyla başlayan kabus: Makam odasında koltuklar havada uçuştu, acı son karakolda geldi",
          "source": "Megabayt",
          "link": "https://www.megabayt.com/otomobil/bir-whatsapp-mesajiyla-baslayan-kabus-makam-odasinda-koltuklar-havada-ucustu-aci-son-karakolda-geldi/102240",
          "also_in": [
            "Megabayt Otomobil"
          ]
        },
        {
          "title": "İkinci el piyasasında ezber bozan karar: Yetki belgesinde eğitim kriteri esnetildi",
          "source": "Megabayt",
          "link": "https://www.megabayt.com/otomobil/ikinci-el-piyasasinda-ezber-bozan-karar-yetki-belgesinde-egitim-kriteri-esnetildi/102235",
          "also_in": [
            "Megabayt Otomobil"
          ]
        },
        {
          "title": "Yurt dışı telefon sahiplerine son uyarı: 54 bin TL ödemeyenlerin cihazı kararıyor",
          "source": "Megabayt",
          "link": "https://www.megabayt.com/teknoloji/yurt-disi-telefon-sahiplerine-son-uyari-54-bin-tl-odemeyenlerin-cihazi-karariyor/102232",
          "also_in": [
            "Megabayt Teknoloji"
          ]
        },
        {
          "title": "5G avcılarına polis darbesi: Milyonluk kuleleri yakmanın bedeli ağır oldu",
          "source": "CHIP Online",
          "link": "https://www.chip.com.tr/guncel/5g-avcilarina-polis-darbesi-milyonluk-kuleleri-yakmanin-bedeli-agir-oldu_179886.html",
          "also_in": []
        },
        {
          "title": "Akreplerin milyonlarca yıllık metal sırrı",
          "source": "CHIP Online",
          "link": "https://www.chip.com.tr/guncel/akreplerin-milyonlarca-yillik-metal-sirri_179904.html",
          "also_in": []
        }
      ]
    },
    {
      "title": "Eğlence ve Kültür Sanat Dünyasındaki Yenilikler",
      "meta_category": "Kültür, Sanat ve Düşünce",
      "summary": "Sinema ve dizi dünyası, yeni film duyuruları, Netflix yapımları ve oyuncu haberleriyle öne çıkarken, müzik listeleri ve festivaller de ilgi gördü. Edebiyat, sanat ve tasarım alanındaki çeşitli etkinlikler ve söyleşiler de kültürel zenginliği yansıttı.",
      "importance": 6,
      "story_count": 100,
      "stories": [
        {
          "title": "Psikolojik Gerilim \"Foxfinder\" İçin Dev Kadro Kuruldu!",
          "source": "Beyaz Perde",
          "link": "https://www.beyazperde.com/haberler/filmler/haberler-1000201945/",
          "also_in": []
        },
        {
          "title": "Robert De Niro ve Adam Scott Başrollü \"Fısıltı Adam\" Netflix’te!",
          "source": "Beyaz Perde",
          "link": "https://www.beyazperde.com/haberler/filmler/haberler-1000201941/",
          "also_in": []
        },
        {
          "title": "Michelle Keegan, Harlan Coben İmzalı \"The Woods\" Kadrosuna Dahil Oldu",
          "source": "Beyaz Perde",
          "link": "https://www.beyazperde.com/haberler/diziler/haberler-1000201912/",
          "also_in": []
        },
        {
          "title": "Kaz Dağları’nın Gölgesinde Sinema Şöleni: İDA Edremit Film Festivali İçin Geri Sayım Başladı",
          "source": "Beyaz Perde",
          "link": "https://www.beyazperde.com/haberler/filmler/haberler-1000201872/",
          "also_in": []
        },
        {
          "title": "TOD'un Yeni Komedisi “Her Şey Mümkün”ün Fragmanı Geldi",
          "source": "Beyaz Perde",
          "link": "https://www.beyazperde.com/haberler/diziler/haberler-1000201868/",
          "also_in": []
        }
      ]
    },
    {
      "title": "Bilim ve Tarihe Yolculuk",
      "meta_category": "Diğer",
      "summary": "İnsanlık tarihine dair ilginç bulgular, eski buluşlar ve bilimsel merak uyandıran konular haberlerde yer aldı. Tarihin gizemleri, bilimsel keşifler ve insanlığın geçmişine ışık tutan araştırmalar bu kümede toplandı.",
      "importance": 4,
      "story_count": 31,
      "stories": [
        {
          "title": "Bu Adam 17.000 Yıl Önce Pusuya Düşürülmüş Olabilir",
          "source": "Arkeofili",
          "link": "https://arkeofili.com/bu-adam-17-000-yil-once-pusuya-dusurulmus-olabilir/?utm_source=rss&utm_medium=rss&utm_campaign=bu-adam-17-000-yil-once-pusuya-dusurulmus-olabilir",
          "also_in": []
        },
        {
          "title": "İspanya’da Hadrianus Duvarı’nı Betimleyen Kase Bulundu",
          "source": "Arkeofili",
          "link": "https://arkeofili.com/ispanyada-hadrianus-duvarini-betimleyen-kase-bulundu/?utm_source=rss&utm_medium=rss&utm_campaign=ispanyada-hadrianus-duvarini-betimleyen-kase-bulundu",
          "also_in": []
        },
        {
          "title": "Şempanzeler Androidlerden Esneme Kapabiliyor",
          "source": "Arkeofili",
          "link": "https://arkeofili.com/sempanzeler-androidlerden-esneme-kapabiliyor/?utm_source=rss&utm_medium=rss&utm_campaign=sempanzeler-androidlerden-esneme-kapabiliyor",
          "also_in": []
        },
        {
          "title": "Tarihin En Kötü İcatları: İyi Niyetle Başlayıp Hüsranla Biten 10 Tasarım",
          "source": "Evrim Ağacı",
          "link": "https://evrimagaci.org/tarihin-en-kotu-icatlari-iyi-niyetle-baslayip-husranla-biten-10-tasarim-22836",
          "also_in": []
        },
        {
          "title": "Hoş Anılarınız Şaşırtıcı Derecede Basit Bir Nedenle Yok Olabilir",
          "source": "Fizikist",
          "link": "https://www.fizikist.com/hos-anilariniz-sasirtici-derecede-basit-bir-nedenle-yok-olabilir",
          "also_in": []
        }
      ]
    },
    {
      "title": "Savunma Sanayii ve Teknolojik İhracat",
      "meta_category": "Savunma ve Sanayi",
      "summary": "Savunma sanayii alanında Otokar'ın Rumen şirketi devralması, HÜRJET'in İspanya'ya ihracatı ve yeni nesil savunma çözümlerinin tanıtımı gibi gelişmeler yaşandı. İHA teknolojileri ve küresel savunma pazarındaki hareketlilik de dikkat çekti.",
      "importance": 4,
      "story_count": 24,
      "stories": [
        {
          "title": "Milli Muharip Uçağı KAAN’a yerli top sistemi desteği",
          "source": "İnternet Haber",
          "link": "https://www.internethaber.com/milli-muharip-ucagi-kaana-yerli-top-sistemi-destegi-video-galerisi-2441498.htm",
          "also_in": [
            "İnternet Haber"
          ]
        },
        {
          "title": "Milli Savunma Bakanlığında \"Savunma Sanayi Değerlendirme Toplantısı\" düzenlendi",
          "source": "İnternet Haber",
          "link": "https://www.internethaber.com/milli-savunma-bakanliginda-savunma-sanayi-degerlendirme-toplantisi-duzenlendi-2441481h.htm",
          "also_in": [
            "Haberler"
          ]
        },
        {
          "title": "Bakan Bayraktar: \"Maden ruhsatlarını iptal edersek işçi kardeşlerimizin faydasına olmaz, istihdam biter\"",
          "source": "Haberler",
          "link": "https://www.haberler.com/politika/bakan-bayraktar-maden-ruhsatlarini-iptal-edersek-19791402-haberi/",
          "also_in": [
            "Medya Gazete"
          ]
        },
        {
          "title": "OTOKAR, Rumen şirketi devraldı",
          "source": "DefenceTurk",
          "link": "https://www.defenceturk.net/otokar-rumen-sirketi-devraldi",
          "also_in": []
        },
        {
          "title": "İspanya’ya HÜRJET ihracatında “Yeni” detaylar: yüzde altmış ne?",
          "source": "DefenceTurk",
          "link": "https://www.defenceturk.net/ispanyaya-hurjet-ihracatinda-yeni-detaylar-yuzde-altmis-ne",
          "also_in": []
        }
      ]
    },
    {
      "title": "Magazin ve Ünlü Haberleri",
      "meta_category": "Magazin ve Eğlence",
      "summary": "Magazin dünyasında ünlülerin yaşamlarına dair haberler, dizi ve film setlerinden gelişmeler, oyuncuların özel hayatlarına dair paylaşımlar ve imaj değişiklikleri yer aldı. Survivor yarışmasındaki gelişmeler de takip edildi.",
      "importance": 3,
      "story_count": 30,
      "stories": [
        {
          "title": "Gizem Karaca ve minik kızı Leyla Yaz'dan yeni kareler geldi",
          "source": "Elele",
          "link": "https://www.elele.com.tr/magazin/gizem-karaca-ve-minik-kizi-leyla-yazdan-yeni-kareler-geldi",
          "also_in": []
        },
        {
          "title": "Çirkin dizisi hangi gün? Çirkin dizisi hangi köyde çekiliyor?",
          "source": "Elele",
          "link": "https://www.elele.com.tr/plus/sinema-televizyon/cirkin-dizisi-hangi-gun-cirkin-dizisi-hangi-koyde-cekiliyor",
          "also_in": []
        },
        {
          "title": "Can Yaman'dan imaj değişikliği! Görenler tanımakta zorlandı",
          "source": "Elele",
          "link": "https://www.elele.com.tr/magazin/can-yamandan-imaj-degisikligi-gorenler-tanimakta-zorlandi",
          "also_in": []
        },
        {
          "title": "Survivor Çağrı Atakan'ın acı günü! Annesi hayatını kaybetti",
          "source": "Elele",
          "link": "https://www.elele.com.tr/magazin/survivor-cagri-atakanin-aci-gunu-annesi-hayatini-kaybetti",
          "also_in": []
        },
        {
          "title": "Yeraltı dizisinde şaşırtan ayrılık! Bir erkek oyuncu veda edecek",
          "source": "Elele",
          "link": "https://www.elele.com.tr/plus/sinema-televizyon/yeralti-dizisinde-sasirtan-ayrilik-bir-erkek-oyuncu-veda-edecek",
          "also_in": []
        }
      ]
    },
    {
      "title": "Sağlık ve Yaşam Tarzı Önerileri",
      "meta_category": "Sağlık",
      "summary": "Sağlık alanında kanser tedavisindeki gelişmelerin yanı sıra, kilo verme önerileri, beslenme alışkanlıkları ve anne-çocuk sağlığına dair konular da haberlerde yer buldu. Yetişkin jimnastiği gibi yaşam tarzı trendleri de dikkat çekti.",
      "importance": 2,
      "story_count": 15,
      "stories": [
        {
          "title": "Kanser tedavisinde ezber bozan gelişme: Bağışıklık sisteminin gizli savunma hattı deşifre edildi",
          "source": "Megabayt",
          "link": "https://www.megabayt.com/teknoloji/kanser-tedavisinde-ezber-bozan-gelisme-bagisiklik-sisteminin-gizli-savunma-hatti-desifre-edildi/102241",
          "also_in": [
            "Megabayt Teknoloji"
          ]
        },
        {
          "title": "Zayıflamak istiyorsan bunları yapma!",
          "source": "A Spor",
          "link": "https://youtube.com/shorts/bQoqG5O_N58?feature=share",
          "also_in": [
            "Fotomaç"
          ]
        },
        {
          "title": "Akreplerin milyonlarca yıllık metal sırrı",
          "source": "CHIP Online",
          "link": "https://www.chip.com.tr/guncel/akreplerin-milyonlarca-yillik-metal-sirri_179904.html",
          "also_in": []
        },
        {
          "title": "Her an gözümüzün önünde olan burnumuzu neden görmüyoruz?",
          "source": "CHIP Online",
          "link": "https://www.chip.com.tr/guncel/her-an-gozumuzun-onunde-olan-burnumuzu-neden-gormuyoruz_179775.html",
          "also_in": []
        },
        {
          "title": "Çernobil'in 40 yıllık sırrı: Radyasyona kafa tutan \"süper kurtlar\"",
          "source": "CHIP Online",
          "link": "https://www.chip.com.tr/guncel/cernobilin-40-yillik-sirri-radyasyona-kafa-tutan-super-kurtlar_179845.html",
          "also_in": []
        }
      ]
    },
    {
      "title": "Eğitim ve Akademik Gelişmeler",
      "meta_category": "Eğitim",
      "summary": "Eğitim alanında LGS örnek sorularının yayımlanması ve okullarda yaşanan olaylara dair araştırma komisyonu gibi konular gündeme geldi. Bilim fuarları ve genç beyinlerin teknoloji şölenleri de eğitim ve inovasyonun önemini vurguladı.",
      "importance": 2,
      "story_count": 5,
      "stories": [
        {
          "title": "Köyceğiz’de genç beyinlerin teknoloji şöleni: Bilim fuarında inovasyon rüzgarları esti",
          "source": "Megabayt",
          "link": "https://www.megabayt.com/teknoloji/koycegizde-genc-beyinlerin-teknoloji-soleni-bilim-fuarinda-inovasyon-ruzgarlari-esti/102237",
          "also_in": [
            "Megabayt Teknoloji"
          ]
        },
        {
          "title": "MEBİ'de LGS öğrencileri için nisan ayı örnek soruları yayımlandı",
          "source": "dikGAZETE",
          "link": "https://www.dikgazete.com/haber/mebi-de-lgs-ogrencileri-icin-nisan-ayi-ornek-sorulari-yayimlandi-998678.html",
          "also_in": [
            "Haber 7",
            "Kamudan Haber"
          ]
        },
        {
          "title": "LGS öğrencileri için hazırlanan nisan ayı örnek soruları MEBİ'de yayımlandı",
          "source": "İnternet Haber",
          "link": "https://www.internethaber.com/lgs-ogrencileri-icin-hazirlanan-nisan-ayi-ornek-sorulari-mebide-yayimlandi-2441509h.htm",
          "also_in": [
            "İstiklal",
            "TRT Haber"
          ]
        },
        {
          "title": "TBMM Okul Saldırılarının Nedenlerini Araştırma Komisyonu ilk toplantısını yaptı",
          "source": "dikGAZETE",
          "link": "https://www.dikgazete.com/haber/tbmm-okul-saldirilarinin-nedenlerini-arastirma-komisyonu-ilk-toplantisini-yapti-998648.html",
          "also_in": [
            "Haberler"
          ]
        },
        {
          "title": "Bartın Organize Sanayi Bölgesi Meslek Yüksekokuluna \"Makine\" programı açıldı",
          "source": "Haberler",
          "link": "https://www.haberler.com/egitim/bartin-organize-sanayi-bolgesi-meslek-19791280-haberi/",
          "also_in": [
            "Medya Gazete"
          ]
        }
      ]
    }
  ],
  "artwork": {
    "title": "The Persistence of Memory",
    "artist": "Salvador Dalí",
    "year": "1931",
    "form": "Painting",
    "medium": "Oil on canvas",
    "location": "Museum of Modern Art (MoMA), New York City",
    "description": "Bu ikonik Sürrealist tablo, ıssız bir manzarada çeşitli nesnelerin üzerine serilmiş eriyen cep saatlerini tasvir ediyor. Zaman, hafıza ve bilinçaltı temalarını ele alan eser, dönemin kaygılarını ve gerçekliğin akışkanlığını yansıtıyor.",
    "verified": true,
    "wikipedia_url": "https://en.wikipedia.org/wiki/The_Persistence_of_Memory",
    "wikipedia_extract": "The Persistence of Memory is a 1931 painting by artist Salvador Dalí and one of the most recognizable works of Surrealism. First exhibited at the Julien Levy Gallery in 1932 and sold for $250, The Persistence of Memory was donated to the Museum of Modern Art (MoMA) in New York City two years later in 1934 by an anonymous donor, where it has remained ever since. It is widely recognized and frequently referred to in popular culture, and sometimes referred to by more descriptive titles, such as \"The Melting Clocks\", \"The Soft Watches\" or \"The Melting Watches\".",
    "image_url": "https://upload.wikimedia.org/wikipedia/en/d/dd/The_Persistence_of_Memory.jpg",
    "artist_wikipedia_url": "https://en.wikipedia.org/wiki/Salvador_Dal%C3%AD"
  },
  "music": {
    "title": "Hurt",
    "artists": "Nine Inch Nails",
    "album": "The Downward Spiral",
    "duration": "6:14",
    "spotify_url": "https://open.spotify.com/track/27tX58NOpv1YKQ0abW7EPy",
    "spotify_id": "27tX58NOpv1YKQ0abW7EPy",
    "album_image": "https://i.scdn.co/image/ab67616d0000b273786dc008f4d6fcf34ca8fd7e",
    "embed_html": "<iframe src=\"https://open.spotify.com/embed/track/27tX58NOpv1YKQ0abW7EPy\" width=\"100%\" height=\"152\" frameborder=\"0\" allowfullscreen allow=\"autoplay; clipboard-write; encrypted-media; fullscreen; picture-in-picture\" loading=\"lazy\"></iframe>",
    "preview_url": null,
    "suggested_genre": "Industrial Rock",
    "suggested_mood": "Melancholy, introspective, raw, powerful"
  },
  "curator_statement": "Bugünün dünyasındaki belirsizlik ve gerilimler, zamanın göreceliği ve insan ruhunun kırılganlığı üzerine düşünmeye sevk ediyor. Salvador Dalí'nin 'Hafızanın Azmi' eseri, eriyen saatleriyle bu zaman algısını görselleştirerek, mevcut küresel karmaşanın yarattığı kaygı ve hayranlık karışımı duyguyu yansıtıyor. Nine Inch Nails'in 'Hurt' parçası ise, bu içsel çalkantıları, yıpranmış ama dirençli bir sesle dile getiriyor. Teknolojinin hızla ilerlediği bir çağda, bu eserler hem bireysel içsel yolculuğumuza hem de kolektif deneyimlerimize ayna tutarak, belirsizlik içinde bir anlam arayışını simgeliyor."
}
